nerf/__init__.py
nerf/nerf.py
pynerf-1.0.4.dist-info/METADATA
pynerf-1.0.4.dist-info/WHEEL
pynerf-1.0.4.dist-info/top_level.txt
pynerf-1.0.4.dist-info/RECORD
