Metadata-Version: 2.1
Name: pynerf
Version: 1.0.4
Summary: A Numpy Implementation of the NeRF Algoritm for Global and Internal Molecular Coordinate Conversion
Home-page: https://github.com/atom-moyer/nerf
Author: Adam Moyer
Author-email: atom.moyer@gmail.com
License: UNKNOWN
Platform: UNKNOWN
Classifier: Programming Language :: Python :: 3
Classifier: Topic :: Scientific/Engineering
Classifier: Topic :: Software Development
Classifier: License :: OSI Approved :: MIT License
Classifier: Operating System :: Unix
Requires-Dist: numpy
